openapi_to_httpx/__init__.py
openapi_to_httpx/cli.py
openapi_to_httpx/generator.py
openapi_to_httpx/naming_strategy.py
openapi_to_httpx/py.typed
openapi_to_httpx/schema_parser.py
openapi_to_httpx/template_renderer.py
openapi_to_httpx/__tests__/__init__.py
openapi_to_httpx/__tests__/conftest.py
openapi_to_httpx/__tests__/fixture_generator.py
openapi_to_httpx/__tests__/test_basic_crud.py
openapi_to_httpx/__tests__/test_edge_cases.py
openapi_to_httpx/__tests__/test_file_upload.py
openapi_to_httpx/__tests__/test_naming_strategy.py
openapi_to_httpx/__tests__/test_petstore.py
openapi_to_httpx/__tests__/test_sse_example.py
openapi_to_httpx/__tests__/fixtures/__init__.py
openapi_to_httpx/__tests__/fixtures/basic_crud.yaml
openapi_to_httpx/__tests__/fixtures/edge_cases.json
openapi_to_httpx/__tests__/fixtures/file_upload.json
openapi_to_httpx/__tests__/fixtures/petstore.json
openapi_to_httpx/__tests__/fixtures/sse_example.json
openapi_to_httpx/__tests__/fixtures/stripe.json
openapi_to_httpx/ast_transform/__init__.py
openapi_to_httpx/ast_transform/transformer.py
openapi_to_httpx/templates/__init__.py
openapi_to_httpx/templates/async_client.py
openapi_to_httpx/templates/base_client.py
openapi_to_httpx/templates/ideal_client.py
openapi_to_httpx/templates/sync_client.py
openapi_to_httpx/templates/output/README.md.j2
openapi_to_httpx/templates/output/__init__.py.j2
openapi_to_httpx/templates/output/cli_success.txt.j2
openapi_to_httpx/templates/output/models.py.j2
openapi_to_httpx-0.1.3.dist-info/METADATA
openapi_to_httpx-0.1.3.dist-info/WHEEL
openapi_to_httpx-0.1.3.dist-info/entry_points.txt
openapi_to_httpx-0.1.3.dist-info/RECORD
