Metadata-Version: 2.4
Name: openapi-to-httpx
Version: 0.1.3
Summary: A simple OpenAPI client generator using AST transformation
Requires-Python: >=3.11
Requires-Dist: click>=8.0
Requires-Dist: httpx>=0.25.0
Requires-Dist: inflection>=0.5.0
Requires-Dist: jinja2>=3.0
Requires-Dist: pydantic>=2.0
Requires-Dist: pyyaml>=6.0
Requires-Dist: ruff>=0.1.0
